lockpass_export.py
lockpass_export-1.0.0.dist-info/entry_points.txt
lockpass_export-1.0.0.dist-info/licenses/COPYING
lockpass_export-1.0.0.dist-info/WHEEL
lockpass_export-1.0.0.dist-info/METADATA
lockpass_export-1.0.0.dist-info/RECORD
