Metadata-Version: 2.4
Name: lockpass-export
Version: 1.0.0
Summary: CLI tool to export LockSelf/LockPass shared passwords
Keywords: lockself,lockpass,password,export,exporter,cli
Author: Wanadev
Requires-Python: >=3.10
License-Expression: GPL-3.0-or-later
License-File: COPYING
Requires-Dist: nox ; extra == "dev"
Requires-Dist: flit ; extra == "dev"
Requires-Dist: black ; extra == "dev"
Requires-Dist: flake8 ; extra == "dev"
Requires-Dist: flake8-pyproject ; extra == "dev"
Requires-Dist: validate-pyproject ; extra == "dev"
Project-URL: changelog, https://github.com/wanadev/lockpass-export?tab=readme-ov-file#changelog
Project-URL: chat, https://discord.gg/BmUkEdMuFp
Project-URL: documentation, https://github.com/wanadev/lockpass-export/blob/master/README.rst
Project-URL: issues, https://github.com/wanadev/lockpass-export/issues
Project-URL: source, https://github.com/wanadev/lockpass-export
Provides-Extra: dev
